card_temps/__init__.py
card_temps/plot_card_temps.py
card_temps/temps.py
card_temps-0.0.1.data/scripts/card_temperatures
card_temps-0.0.1.dist-info/METADATA
card_temps-0.0.1.dist-info/WHEEL
card_temps-0.0.1.dist-info/top_level.txt
card_temps-0.0.1.dist-info/RECORD
