Metadata-Version: 2.1
Name: card-temps
Version: 0.0.1
Summary: A package to analyze and report on the FPGA card temperatures of the Gatan K3 camera.
Home-page: https://github.com/matthutchison/card_temps
Author: Matt Hutchison
Author-email: matt.hutchison@gmail.com
License: UNKNOWN
Platform: UNKNOWN
Classifier: License :: OSI Approved :: MIT License
Classifier: Operating System :: OS Independent
Classifier: Development Status :: 3 - Alpha
Classifier: Intended Audience :: Science/Research
Requires-Python: >=3.6
